alimiji_filmns_sdk/__init__.py
alimiji_filmns_sdk/film_client.py
alimiji_filmns_sdk/film_config.py
alimiji_filmns_sdk/schemas/__init__.py
alimiji_filmns_sdk/schemas/schemas.py
alimiji_filmns_sdk-0.0.3.dist-info/METADATA
alimiji_filmns_sdk-0.0.3.dist-info/WHEEL
alimiji_filmns_sdk-0.0.3.dist-info/top_level.txt
alimiji_filmns_sdk-0.0.3.dist-info/RECORD
